Metadata-Version: 1.0
Name: py-tsharp
Version: 1.0.1
Summary: A CLI for The T# Language (Made by me)
Home-page: UNKNOWN
Author: UNKNOWN
Author-email: UNKNOWN
License: UNKNOWN
Platform: UNKNOWN
